pymdown_toc_ext.py
pymdown_toc_ext-1.3.1.dist-info/entry_points.txt
pymdown_toc_ext-1.3.1.dist-info/LICENSE
pymdown_toc_ext-1.3.1.dist-info/WHEEL
pymdown_toc_ext-1.3.1.dist-info/METADATA
pymdown_toc_ext-1.3.1.dist-info/RECORD
